{
  "dashboard1": {
    "abc": {
      "labels": ["A", "B", "C"],
      "values": [500000, 300000, 100000]
    },
    "fsn": {
      "labels": ["Fast", "Slow", "Non-moving"],
      "counts": [40, 30, 10]
    },
    "turnover": {
      "months": ["Jan", "Feb", "Mar", "Apr"],
      "values": [3.2, 3.5, 3.1, 3.8]
    },
    "doi": {
      "items": ["Item A", "Item B", "Item C"],
      "values": [60, 45, 90]
    },
    "risk": {
      "labels": ["Obsolete", "Slow-moving", "Short Shelf Life"],
      "values": [150000, 100000, 50000]
    }
  },
  "dashboard2": {
    "labels": ["Jan", "Feb", "Mar"],
    "accuracy": [0.8, 0.75, 0.82]
  },
  "dashboard3": {
    "labels": ["Reduced Stock", "Auto Replenish", "Improved Accuracy"],
    "values": [40, 35, 25]
  }
}
